<?xml version="1.0" encoding="UTF-8"?>
<MOBILY_BSL_SR>
	<SR_HEADER>
		<FuncId>CUG_SUBSCRIBE</FuncId>
		<SecurityKey>0000</SecurityKey>
		<RequestorChannelId>SIEBEL</RequestorChannelId>
		<SrDate>20081221181907</SrDate>
		<UserId/>
		<OverwriteOpenOrder/>
		<Chargeable>N</Chargeable>
		<ChargeAmount>0.0</ChargeAmount>
		<Reason>NotForIUCCR3</Reason>
	</SR_HEADER>
	<LinesInfo>
		<Line/>
	</LinesInfo>
	<ChannelTransId>1-8594591190</ChannelTransId>
	<SupplementaryService/>
	<operation>subscribe</operation>
	<CorporateId/>
	<CUG_Id/>
	<MSISDN_LIST>
		<MSISDN/>
		<PACKAGE_ID>5001</PACKAGE_ID>
	</MSISDN_LIST>
</MOBILY_BSL_SR>
