<?xml version="1.0" encoding="UTF-8"?>
<MOBILY_BSL_SR>
	<SR_HEADER>
		<FuncId>PRE2PRE_CONV</FuncId>
		<MsgVersion>0000</MsgVersion>
		<RequestorChannelId>BSL</RequestorChannelId>
		<ServiceRequestId>SR_3032319799</ServiceRequestId>
		<SrDate>20110705090750</SrDate>
		<RequestorUserId>db2admin</RequestorUserId>
		<RequestorLanguage>E</RequestorLanguage>
		<ReturnCode>0000</ReturnCode>
	</SR_HEADER>
	<MSISDN>200903554584</MSISDN>
	<OldPackageId>1197</OldPackageId>
	<OldPackageName>Sky Walker 5G - Prepaid</OldPackageName>
	<NewPackageId>1456</NewPackageId>
	<NewPackageName>Prepaid_Connect_2GB</NewPackageName>
	<IMEI/>
</MOBILY_BSL_SR>
